terminalpy/__init__.py
terminalpy/terminalpy.py
terminalpyth-2.1.0.dist-info/LICENSE
terminalpyth-2.1.0.dist-info/METADATA
terminalpyth-2.1.0.dist-info/WHEEL
terminalpyth-2.1.0.dist-info/top_level.txt
terminalpyth-2.1.0.dist-info/RECORD
