Metadata-Version: 2.1
Name: terminalpyth
Version: 2.1.0
Summary: Terminal extension for python
Author: Cargo
License: MIT
Platform: UNKNOWN
